odoo8_addon_product_variant_available_in_pos-8.0.1.0.0-py2.7-nspkg.pth
odoo8_addon_product_variant_available_in_pos-8.0.1.0.0.dist-info/top_level.txt
odoo8_addon_product_variant_available_in_pos-8.0.1.0.0.dist-info/WHEEL
odoo8_addon_product_variant_available_in_pos-8.0.1.0.0.dist-info/RECORD
odoo8_addon_product_variant_available_in_pos-8.0.1.0.0.dist-info/metadata.json
odoo8_addon_product_variant_available_in_pos-8.0.1.0.0.dist-info/DESCRIPTION.rst
odoo8_addon_product_variant_available_in_pos-8.0.1.0.0.dist-info/METADATA
odoo8_addon_product_variant_available_in_pos-8.0.1.0.0.dist-info/namespace_packages.txt
odoo_addons/product_variant_available_in_pos/__openerp__.py
odoo_addons/product_variant_available_in_pos/hooks.py
odoo_addons/product_variant_available_in_pos/__init__.py
odoo_addons/product_variant_available_in_pos/README.rst
odoo_addons/product_variant_available_in_pos/models/product_template.py
odoo_addons/product_variant_available_in_pos/models/product_product.py
odoo_addons/product_variant_available_in_pos/models/__init__.py
odoo_addons/product_variant_available_in_pos/i18n/it.po
odoo_addons/product_variant_available_in_pos/tests/test_product_variant_available_in_pos.py
odoo_addons/product_variant_available_in_pos/tests/__init__.py
odoo_addons/product_variant_available_in_pos/static/description/icon.png
